python_multirunner/__init__.py
python_multirunner/executor.py
python_multirunner/future.py
python_multirunner/primitives.py
python_multirunner-0.1.1.dist-info/licenses/LICENSE
python_multirunner-0.1.1.dist-info/METADATA
python_multirunner-0.1.1.dist-info/WHEEL
python_multirunner-0.1.1.dist-info/top_level.txt
python_multirunner-0.1.1.dist-info/RECORD
