Metadata-Version: 2.4
Name: python-multirunner
Version: 0.1.1
Summary: A high-performance hybrid executor for Python 3.13+ without GIL, supporting CPU-bound and async/await operations with work stealing and priority queues
Author-email: Raphael Raasch <devraasch@gmail.com>
License-Expression: MIT
Project-URL: Homepage, https://gitlab.com/bytenestti/python_multirunner
Project-URL: Repository, https://gitlab.com/bytenestti/python_multirunner.git
Project-URL: Issues, https://gitlab.com/bytenestti/python_multirunner/-/issues
Project-URL: Documentation, https://gitlab.com/bytenestti/python_multirunner
Keywords: concurrency,parallelism,async,executor,threading,gil-free
Classifier: Development Status :: 4 - Beta
Classifier: Intended Audience :: Developers
Classifier: Operating System :: OS Independent
Classifier: Programming Language :: Python :: 3
Classifier: Programming Language :: Python :: 3.12
Classifier: Topic :: Software Development :: Libraries :: Python Modules
Classifier: Topic :: System :: Distributed Computing
Requires-Python: >=3.12
License-File: LICENSE
Requires-Dist: build>=1.3.0
Requires-Dist: psutil>=5.9.0
Requires-Dist: pytest>=8.4.2
Requires-Dist: twine>=6.2.0
Provides-Extra: dev
Requires-Dist: pytest>=7.0.0; extra == "dev"
Requires-Dist: pytest-asyncio>=0.21.0; extra == "dev"
Requires-Dist: pytest-cov>=4.0.0; extra == "dev"
Requires-Dist: black>=23.0.0; extra == "dev"
Requires-Dist: isort>=5.12.0; extra == "dev"
Requires-Dist: flake8>=6.0.0; extra == "dev"
Requires-Dist: mypy>=1.0.0; extra == "dev"
Requires-Dist: safety>=2.0.0; extra == "dev"
Requires-Dist: bandit>=1.7.0; extra == "dev"
Provides-Extra: docs
Requires-Dist: sphinx>=6.0.0; extra == "docs"
Requires-Dist: sphinx-rtd-theme>=1.2.0; extra == "docs"
Requires-Dist: myst-parser>=1.0.0; extra == "docs"
Dynamic: license-file
